nonebot_plugin_kawaii_status-0.1.9.dist-info/METADATA
nonebot_plugin_kawaii_status-0.1.9.dist-info/WHEEL
nonebot_plugin_kawaii_status-0.1.9.dist-info/licenses/LICENSE
nonebot_plugin_kawaii_status/__init__.py
nonebot_plugin_kawaii_status/color.py
nonebot_plugin_kawaii_status/config.py
nonebot_plugin_kawaii_status/drawer.py
nonebot_plugin_kawaii_status/model.py
nonebot_plugin_kawaii_status/path.py
nonebot_plugin_kawaii_status/resources/fonts/ADLaMDisplay-Regular.ttf
nonebot_plugin_kawaii_status/resources/fonts/SpicyRice-Regular.ttf
nonebot_plugin_kawaii_status/resources/fonts/baotu.ttf
nonebot_plugin_kawaii_status/resources/images/background.png
nonebot_plugin_kawaii_status/resources/images/marker.png
nonebot_plugin_kawaii_status/utils.py
nonebot_plugin_kawaii_status-0.1.9.dist-info/RECORD
