Metadata-Version: 2.1
Name: nonebot-plugin-kawaii-status
Version: 0.1.9
Summary: NoneBot2 服务器状态查看插件 / View server status for NoneBot2
Home-page: https://github.com/KomoriDev/nonebot-plugin-kawaii-status
Author-Email: KomoriDev <mute231010@gmail.com>
License: MIT
Project-URL: Homepage, https://github.com/KomoriDev/nonebot-plugin-kawaii-status
Project-URL: Repository, https://github.com/KomoriDev/nonebot-plugin-kawaii-status
Requires-Python: >=3.9
Requires-Dist: nonebot-plugin-alconna>=0.52.1
Requires-Dist: psutil>=5.9.8
Requires-Dist: pillow>=10.2.0
Requires-Dist: nonebot2[fastapi]>=2.2.0
Requires-Dist: py-cpuinfo>=9.0.0
Requires-Dist: nonebot-adapter-onebot>=2.4.1; extra == "adapters"
Provides-Extra: adapters
